pydbmtools/__init__.py
pydbmtools/configs.py
pydbmtools/main.py
pydbmtools/static.py
pydbmtools-0.0.3.dist-info/LICENSE
pydbmtools-0.0.3.dist-info/METADATA
pydbmtools-0.0.3.dist-info/WHEEL
pydbmtools-0.0.3.dist-info/entry_points.txt
pydbmtools-0.0.3.dist-info/top_level.txt
pydbmtools-0.0.3.dist-info/RECORD
